configs/__init__.py
configs/montages.yaml
autoclean/__init__.py
autoclean/__main__.py
autoclean/cli.py
autoclean/calc/assr_analysis.py
autoclean/calc/assr_runner.py
autoclean/calc/assr_viz.py
autoclean/calc/source.py
autoclean/configkit/__init__.py
autoclean/configkit/schema.py
autoclean/core/__init__.py
autoclean/core/pipeline.py
autoclean/core/task.py
autoclean/functions/__init__.py
autoclean/functions/advanced/__init__.py
autoclean/functions/advanced/autoreject.py
autoclean/functions/analysis/__init__.py
autoclean/functions/analysis/statistical_learning.py
autoclean/functions/artifacts/__init__.py
autoclean/functions/artifacts/channels.py
autoclean/functions/epoching/__init__.py
autoclean/functions/epoching/eventid.py
autoclean/functions/epoching/quality.py
autoclean/functions/epoching/regular.py
autoclean/functions/epoching/statistical.py
autoclean/functions/epoching/statistical_randomized.py
autoclean/functions/ica/__init__.py
autoclean/functions/ica/ica_processing.py
autoclean/functions/preprocessing/__init__.py
autoclean/functions/preprocessing/basic_ops.py
autoclean/functions/preprocessing/filtering.py
autoclean/functions/preprocessing/referencing.py
autoclean/functions/preprocessing/resampling.py
autoclean/functions/preprocessing/wavelet_thresholding.py
autoclean/functions/segment_rejection/__init__.py
autoclean/functions/segment_rejection/dense_oscillatory.py
autoclean/functions/segment_rejection/segment_rejection.py
autoclean/functions/visualization/__init__.py
autoclean/functions/visualization/icvision_layouts.py
autoclean/functions/visualization/plotting.py
autoclean/functions/visualization/reports.py
autoclean/io/__init__.py
autoclean/io/export.py
autoclean/io/import_.py
autoclean/mixins/__init__.py
autoclean/mixins/base.py
autoclean/mixins/analysis/__init__.py
autoclean/mixins/analysis/inter_trial_coherence.py
autoclean/mixins/reporting/__init__.py
autoclean/mixins/reporting/combined_image.py
autoclean/mixins/signal_processing/__init__.py
autocleaneeg_pipeline-2.3.0.dist-info/METADATA
autocleaneeg_pipeline-2.3.0.dist-info/WHEEL
autocleaneeg_pipeline-2.3.0.dist-info/entry_points.txt
autocleaneeg_pipeline-2.3.0.dist-info/licenses/LICENSE
autocleaneeg_pipeline-2.3.0.dist-info/RECORD
