Metadata-Version: 2.4
Name: autocleaneeg-pipeline
Version: 2.3.0
Summary: A modular framework for automated EEG data processing, built on MNE-Python
Project-URL: Homepage, https://github.com/cincibrainlab/autoclean_pipeline
Project-URL: Repository, https://github.com/cincibrainlab/autoclean_pipeline
Project-URL: Documentation, https://cincibrainlab.github.io/autoclean_pipeline/
Project-URL: Issues, https://github.com/cincibrainlab/autoclean_pipeline/issues
Author-email: Ernest Pedapati <ernest.pedapati@cchmc.org>, Gavin Gammoh <gavin.gammoh@cchmc.org>
License: MIT License
License-File: LICENSE
Keywords: bids,eeg,electrophysiology,mne-python,neuroscience,preprocessing,signal-processing
Classifier: Development Status :: 4 - Beta
Classifier: Intended Audience :: Science/Research
Classifier: License :: OSI Approved :: MIT License
Classifier: Programming Language :: Python :: 3
Classifier: Programming Language :: Python :: 3.10
Classifier: Programming Language :: Python :: 3.11
Classifier: Programming Language :: Python :: 3.12
Classifier: Topic :: Scientific/Engineering :: Bio-Informatics
Classifier: Topic :: Scientific/Engineering :: Medical Science Apps.
Requires-Python: <3.14,>=3.10
Requires-Dist: auth0-python>=4.7.1
Requires-Dist: autoclean-eeg2source>=0.1.0
Requires-Dist: autocleaneeg-icvision>=0.1.0
Requires-Dist: autocleaneeg-view
Requires-Dist: autoreject>=0.3.0
Requires-Dist: bctpy>=0.6.1
Requires-Dist: cryptography>=3.4.8
Requires-Dist: cython>=0.29.0
Requires-Dist: defusedxml
Requires-Dist: eeglabio>=0.0.3
Requires-Dist: fastparquet>=2024.11.0
Requires-Dist: fastplotlib>=0.3.0
Requires-Dist: fooof>=1.1.0
Requires-Dist: inquirer>=3.1.0
Requires-Dist: loguru>=0.6.0
Requires-Dist: matplotlib>=3.4.0
Requires-Dist: mne-bids>=0.10
Requires-Dist: mne-connectivity>=0.7.0
Requires-Dist: mne-icalabel>=0.8.0
Requires-Dist: mne-qt-browser>=0.3.0
Requires-Dist: mne>=1.7.0
Requires-Dist: networkx>=3.4.2
Requires-Dist: nibabel>=5.3.2
Requires-Dist: numpy>=1.20.0
Requires-Dist: onnxruntime>=1.22.1
Requires-Dist: openai>=1.78.1
Requires-Dist: pandas>=1.3.0
Requires-Dist: pillow>=9.0.0
Requires-Dist: platformdirs>=3.0.0
Requires-Dist: pybv>=0.6.0
Requires-Dist: pydantic>=2.0
Requires-Dist: pyjsonviewer>=0.1.0
Requires-Dist: pymupdf
Requires-Dist: pymupdf>=1.0.0
Requires-Dist: pyopengl-accelerate
Requires-Dist: pyprep>=0.3.0
Requires-Dist: pyqt5>=5.15.11
Requires-Dist: python-dotenv>=0.19.0
Requires-Dist: python-picard==0.8
Requires-Dist: python-ulid>=1.0.0
Requires-Dist: pyvistaqt>=0.11.2
Requires-Dist: pywavelets>=1.5.0
Requires-Dist: pyyaml>=5.1
Requires-Dist: qtpy>=2.4.3
Requires-Dist: reportlab>=3.6.0
Requires-Dist: requests>=2.25.0
Requires-Dist: rich>=10.0.0
Requires-Dist: schema>=0.7.0
Requires-Dist: scipy>=1.7.0
Requires-Dist: seaborn>=0.13.2
Requires-Dist: textual-dev>=0.11.0
Requires-Dist: textual>=0.11.0
Requires-Dist: torch>=1.9.0
